pythonadb/__init__.py
pythonadb/_logger.py
pythonadb/_version.py
pythonadb/adb_client.py
pythonadb/adb_device.py
pythonadb/am.py
pythonadb/constants.py
pythonadb/intent.py
pythonadb/keycodes.py
pythonadb/packageparser.py
pythonadb/pm.py
pythonadb/propertyparser.py
pythonadb/types.py
pythonadb/adb_connection/__init__.py
pythonadb/events/__init__.py
pythonadb/events/_adb_connection_event.py
pythonadb-0.0.27.dist-info/LICENSE
pythonadb-0.0.27.dist-info/METADATA
pythonadb-0.0.27.dist-info/WHEEL
pythonadb-0.0.27.dist-info/top_level.txt
pythonadb-0.0.27.dist-info/RECORD
