Metadata-Version: 2.1
Name: pythonadb
Version: 0.0.27
Summary: pure python adb client for mac/win/linux
Home-page: https://github.com/sephiroth74/python-adb-client
Author: Alessandro Crugnola
Author-email: alessandro.crugnola@gmail.com
License: MIT
Classifier: Programming Language :: Python :: 3
Classifier: License :: OSI Approved :: MIT License
Classifier: Operating System :: OS Independent
Requires-Python: >=3.8
License-File: LICENSE
Requires-Dist: coloredlogs (>=15.0.1)
Requires-Dist: optional.py (>=1.3.2)
Requires-Dist: verboselogs (>=1.7)
Requires-Dist: zope.event (>=4.5.0)
